lforchiniHTTP
