Metadata-Version: 2.1
Name: lforchiniHTTP
Version: 0.0.9
Summary: A simple HTTP server with a custom handler
Home-page: https://github.com/lforchini/HTTP-Server
Author: LForchini
Author-email: leonardo.forchini@gmail.com
License: UNKNOWN
Platform: UNKNOWN
Classifier: Programming Language :: Python :: 3
Classifier: License :: OSI Approved :: MIT License
Classifier: Operating System :: OS Independent
